floryn/__init__.py
floryn/floryn.py
floryn-0.1.0.dist-info/METADATA
floryn-0.1.0.dist-info/WHEEL
floryn-0.1.0.dist-info/top_level.txt
floryn-0.1.0.dist-info/RECORD
