Metadata-Version: 2.1
Name: floryn
Version: 0.1.0
Summary: Plot proportionally filled text with color
Author-email: M Iqbal Tawakal <mit.iqi@gmail.com>
Project-URL: Repository, https://github.com/mitbal/floryn.git
Keywords: matplotlib,plot,data science,visualization
Classifier: License :: OSI Approved :: MIT License
Classifier: Programming Language :: Python :: 3
Classifier: Operating System :: OS Independent
Requires-Python: >=3.9
Requires-Dist: numpy >=1.26.4
Requires-Dist: seaborn >=0.13.2
Requires-Dist: matplotlib >=3.9.0
Requires-Dist: scikit-image >=0.24.0
